matrix_webcam/__init__.py
matrix_webcam/__main__.py
matrix_webcam-0.4.2.dist-info/LICENSE
matrix_webcam-0.4.2.dist-info/METADATA
matrix_webcam-0.4.2.dist-info/WHEEL
matrix_webcam-0.4.2.dist-info/entry_points.txt
matrix_webcam-0.4.2.dist-info/top_level.txt
matrix_webcam-0.4.2.dist-info/RECORD
