Metadata-Version: 2.1
Name: matrix-webcam
Version: 0.4.2
Summary: Displays your webcam video feed in the console.
Home-page: https://github.com/joschuck/matrix-webcam
Author: Johannes Schuck
Author-email: jojoschuck@gmail.com
License: MIT License        
Keywords: matrix webcam opencv skype
Classifier: License :: OSI Approved :: MIT License
Classifier: Programming Language :: Python
Classifier: Programming Language :: Python :: 3
License-File: LICENSE
Requires-Dist: numpy (~=1.20)
Requires-Dist: opencv-contrib-python (~=4.5.4)
Requires-Dist: mediapipe (~=0.8)
Requires-Dist: windows-curses (~=2.3) ; platform_system == "Windows"
Provides-Extra: deploy
Requires-Dist: wheel ; extra == 'deploy'
Requires-Dist: twine ; extra == 'deploy'
Requires-Dist: build ; extra == 'deploy'
Requires-Dist: setuptools ; extra == 'deploy'
Provides-Extra: dev
Requires-Dist: pre-commit ; extra == 'dev'
Requires-Dist: pylint ; extra == 'dev'
Requires-Dist: black (~=22.3.0) ; extra == 'dev'
Requires-Dist: mypy ; extra == 'dev'
